glean/__init__.py
glean/__main__.py
glean/cmd.py
glean/install.py
glean/systemlock.py
glean/utils.py
glean/_vendor/__init__.py
glean/_vendor/distro.py
glean/init/__init__.py
glean/init/glean-early.service
glean/init/glean-early.sh
glean/init/glean-legacy.sh
glean/init/glean-networkd.service
glean/init/glean-nm@.service
glean/init/glean-udev.rules
glean/init/glean.conf
glean/init/glean.init
glean/init/glean.openrc
glean/init/glean@.service
glean/init/nm-no-resolv-handling.conf
glean/init/nm-udev-settle.override
glean/init/python-glean.template
glean/tests/__init__.py
glean/tests/test_glean.py
glean/tests/fixtures/README.rst
glean/tests/fixtures/hp/mnt/config/openstack/latest/meta_data.json
glean/tests/fixtures/hp/mnt/config/openstack/latest/vendor_data.json
glean/tests/fixtures/hp/sys/class/net/eth0/addr_assign_type
glean/tests/fixtures/hp/sys/class/net/eth0/address
glean/tests/fixtures/hp/sys/class/net/eth0/carrier
glean/tests/fixtures/hp/sys/class/net/eth1/addr_assign_type
glean/tests/fixtures/hp/sys/class/net/eth1/address
glean/tests/fixtures/hp/sys/class/net/eth1/carrier
glean/tests/fixtures/hp/sys/class/net/eth2/addr_assign_type
glean/tests/fixtures/hp/sys/class/net/eth2/address
glean/tests/fixtures/hp/sys/class/net/eth2/carrier
glean/tests/fixtures/hp/sys/class/net/eth3/addr_assign_type
glean/tests/fixtures/hp/sys/class/net/eth3/address
glean/tests/fixtures/hp/sys/class/net/eth3/carrier
glean/tests/fixtures/liberty/mnt/config/openstack/latest/meta_data.json
glean/tests/fixtures/liberty/mnt/config/openstack/latest/network_info.json
glean/tests/fixtures/liberty/mnt/config/openstack/latest/vendor_data.json
glean/tests/fixtures/liberty/sys/class/net/eth0/addr_assign_type
glean/tests/fixtures/liberty/sys/class/net/eth0/address
glean/tests/fixtures/liberty/sys/class/net/eth0/carrier
glean/tests/fixtures/liberty/sys/class/net/eth1/addr_assign_type
glean/tests/fixtures/liberty/sys/class/net/eth1/address
glean/tests/fixtures/liberty/sys/class/net/eth1/carrier
glean-1.25.1.dist-info/AUTHORS
glean-1.25.1.dist-info/LICENSE
glean-1.25.1.dist-info/METADATA
glean-1.25.1.dist-info/WHEEL
glean-1.25.1.dist-info/entry_points.txt
glean-1.25.1.dist-info/pbr.json
glean-1.25.1.dist-info/top_level.txt
glean-1.25.1.dist-info/RECORD
